smolALU.sv
/*
    Author: Ricardo Vergel
    Description: ALU for SmolCore supporting all the operations
    Date: April 18-2025

    ****INSERT YOUR CHANGES BELOW****
    Date: April 19-2025
    Description: Added branch enable on alu_out LSB

	Date: April 22-2025
	Description: Modification for Branch, AUIPC, JAL operations logic.
*/

/* verilator lint_off WIDTHTRUNC */
/* verilator lint_off WIDTHEXPAND */
/* verilator lint_off UNUSEDSIGNAL */

module smolALU(
    input logic [31:0] rs1,
    input logic [31:0] rs2_or_imm,
    input logic [4:0] pc,
    input logic [4:0] op_sel,
    output logic [31:0] alu_out
  //  output logic carry,
  //  output logic overflow
    
);


always_comb begin

 // internal signals for add/sub
    logic [32:0] sum_ext;
    logic signed [31:0] a_s, b_s, sum_s;
    logic [63:0] sra_aux;
    
  // extend to capture carry
    sum_ext = (op_sel == 5'd1) 
                   ? ({1'b0, rs1} - {1'b0, rs2_or_imm}) 
                   : ({1'b0, rs1} + {1'b0, rs2_or_imm});

  // signed version for overflow detection
    a_s    = rs1;
    b_s    = (op_sel == 5'd1) ? -rs2_or_imm : rs2_or_imm;
    sum_s  = a_s + b_s;
    sra_aux = 64'd0;
    case (op_sel)
        5'd0: begin
            alu_out = rs1 + rs2_or_imm; //add or addi
        end
        5'd1: begin
            alu_out = rs1 - rs2_or_imm; //sub
        end
        5'd2: begin
            alu_out = rs1 & rs2_or_imm; //and or andi
        end
        5'd3: begin
            alu_out = rs1 || rs2_or_imm; //or or ori
        end
        5'd4: begin
            alu_out = rs1 ^ rs2_or_imm; //xor or xori
        end
        5'd5: begin
            alu_out = rs1 >> rs2_or_imm[4:0]; //srli or srl
        end
        5'd6: begin
            alu_out = rs1 << rs2_or_imm[4:0]; //slli or slli
        end
        5'd7: begin
            alu_out = {31'b0, rs1 < rs2_or_imm}; //sltu or sltiu
        end
        5'd8: begin
            alu_out = {rs2_or_imm[31:12],12'b0}; //lui
        end
        5'd9: begin
            alu_out = pc + rs2_or_imm; //auipc
        end
        5'd10: begin
            alu_out = pc + 32'd4; //jal or jalr
        end
        5'd11: begin
            alu_out = (rs1[31] == rs2_or_imm[31]) ? {31'b0, rs1 < rs2_or_imm} : {31'b0, rs1[31]}; //slt or slti
        end
        5'd12: begin
            sra_aux = {{32{rs1[31]}},rs1} >> rs2_or_imm[4:0];
            alu_out = sra_aux[31:0]; //sra or srai
        end
        5'd13: begin
            alu_out = rs1 + rs2_or_imm; //load or store address
        end
        5'd14: begin
            alu_out = rs1 == rs2_or_imm ? pc + rs2_or_imm : 32'd0; //beq
        end
        5'd15: begin
            alu_out = rs1 != rs2_or_imm ? pc + rs2_or_imm : 32'd0; //bne
        end
        5'd16: begin
            alu_out = (rs1 < rs2_or_imm) ^ (rs1[31] != rs2_or_imm[31]) ? pc + rs2_or_imm : 32'd0 ; //blt
        end
        5'd17: begin
            alu_out = (rs1 >= rs2_or_imm) ^ (rs1[31] != rs2_or_imm[31]) ? pc + rs2_or_imm : 32'd0; //bge
        end
        5'd18: begin
            alu_out = rs1 < rs2_or_imm ? pc + rs2_or_imm : 32'd0; //bltu
        end
        5'd19: begin
            alu_out = rs1 >= rs2_or_imm ? pc + rs2_or_imm : 32'd0; //bgeu
        end
         
        default: begin
            alu_out = 32'h0000_0000;
        end
    endcase
end
endmodule

ALUwaveform.vcd
$version Generated by VerilatedVcd $end
$timescale 1ps $end
 $scope module TOP $end
  $var wire 32 ( rs1 [31:0] $end
  $var wire 32 ) rs2_or_imm [31:0] $end
  $var wire 5 * pc [4:0] $end
  $var wire 5 + op_sel [4:0] $end
  $var wire 32 , alu_out [31:0] $end
  $scope module smolALU $end
   $var wire 32 ( rs1 [31:0] $end
   $var wire 32 ) rs2_or_imm [31:0] $end
   $var wire 5 * pc [4:0] $end
   $var wire 5 + op_sel [4:0] $end
   $var wire 32 , alu_out [31:0] $end
   $scope module unnamedblk1 $end
    $var wire 33 - sum_ext [32:0] $end
    $var wire 32 # a_s [31:0] $end
    $var wire 32 $ b_s [31:0] $end
    $var wire 32 % sum_s [31:0] $end
    $var wire 64 & sra_aux [63:0] $end
   $upscope $end
  $upscope $end
 $upscope $end
$enddefinitions $end


#0
b00000000000000000000000000001010 #
b00000000000000000000000000000100 $
b00000000000000000000000000001110 %
b0000000000000000000000000000000000000000000000000000000000000000 &
b00000000000000000000000000001010 (
b00000000000000000000000000000100 )
b01100 *
b00000 +
b00000000000000000000000000001110 ,
b000000000000000000000000000001110 -
#1
b11111111111111111111111111111100 $
b00000000000000000000000000000110 %
b00001 +
b00000000000000000000000000000110 ,
b000000000000000000000000000000110 -
#2
b00000000000000000000000000000100 $
b00000000000000000000000000001110 %
b00010 +
b00000000000000000000000000000000 ,
b000000000000000000000000000001110 -
#3
b00011 +
b00000000000000000000000000000001 ,
#4
b00100 +
b00000000000000000000000000001110 ,
#5
b00101 +
b00000000000000000000000000000000 ,
#6
b00110 +
b00000000000000000000000010100000 ,
#7
b00111 +
b00000000000000000000000000000000 ,
#8
b01000 +
#9
b01001 +
b00000000000000000000000000010000 ,
#10
b01010 +
#11
b01011 +
b00000000000000000000000000000000 ,
#12
b01100 +
#13
b01101 +
b00000000000000000000000000001110 ,
#14
b01110 +
b00000000000000000000000000000000 ,
#15
b01111 +
b00000000000000000000000000010000 ,
#16
b10000 +
b00000000000000000000000000000000 ,
#17
b10001 +
b00000000000000000000000000010000 ,
#18
b10010 +
b00000000000000000000000000000000 ,
#19
b10011 +
b00000000000000000000000000010000 ,
