smolNextPC.sv
/*
    Author: Ricardo Vergel
    Description: Next PC Logic calculator with branch and jump instruction
    Date: April 19-2025

    ****INSERT YOUR CHANGES BELOW***

	Date: April 22-2025
	Description: Branch and AUIPC operations supported in ALU, Jal operation calculated locally
*/
module smolNextPC(
    input logic [31:0] rs1,
    input logic [31:0] rs2_or_imm,
    input logic [31:0] pc,
	input logic [31:0] alu_out,
    input logic br_auipc_enable, //from control
	input logic jal_enable, //from control
    input logic rst,

    output logic [31:0] nextPC
);

assign nextPC = rst ? 32'd0 : br_auipc_enable ? alu_out
                            : jal_enable ? rs1 + rs2_or_imm 
							: pc + 32'd4; 

endmodule

NextPCwave.vcd
$version Generated by VerilatedVcd $end
$timescale 1ps $end
 $scope module TOP $end
  $var wire 32 # rs1 [31:0] $end
  $var wire 32 $ rs2_or_imm [31:0] $end
  $var wire 32 % pc [31:0] $end
  $var wire 32 & alu_out [31:0] $end
  $var wire 1 ' br_auipc_enable $end
  $var wire 1 ( jal_enable $end
  $var wire 1 ) rst $end
  $var wire 32 * nextPC [31:0] $end
  $scope module smolNextPC $end
   $var wire 32 # rs1 [31:0] $end
   $var wire 32 $ rs2_or_imm [31:0] $end
   $var wire 32 % pc [31:0] $end
   $var wire 32 & alu_out [31:0] $end
   $var wire 1 ' br_auipc_enable $end
   $var wire 1 ( jal_enable $end
   $var wire 1 ) rst $end
   $var wire 32 * nextPC [31:0] $end
  $upscope $end
 $upscope $end
$enddefinitions $end


#0
b00000000000000000000000000000000 #
b00000000000000000000000000000000 $
b00000000000000000000000000000000 %
b00000000000000000000000000000000 &
0'
0(
0)
b00000000000000000000000000000100 *
#1
#2
#3
#4
#5
b00000000000000000000000000001010 #
b00000000000000000000000000000010 $
1(
b00000000000000000000000000001100 *
#6
0(
b00000000000000000000000000000100 *
#7
#8
b00000000000000000000000001100100 &
1'
b00000000000000000000000001100100 *
#9
#10
b00000000000000000000000000001000 &
b00000000000000000000000000001000 *
#11
0'
b00000000000000000000000000000100 *
#12
1)
b00000000000000000000000000000000 *
#13
0)
b00000000000000000000000000000100 *
