smolInsMem.sv
//------------------------------------------------------------------------------
// File: InstructionMemory.sv
// A parameterizable instruction ROM with optional synchronous output.
// SOURCE: CHATGPT KEKW
//------------------------------------------------------------------------------
/* verilator lint_off DECLFILENAME */
/* verilator lint_off UNUSEDSIGNAL */

module InstructionMemory #(
  parameter ADDR_WIDTH = 10,       // how many bits of word address (2^ADDR_WIDTH words)
  parameter DATA_WIDTH = 32,       // instruction width
  parameter MEM_FILE   = "program.hex", // initialization file (in hex)
  parameter SYNC_READ  = 1         // 0 = async read, 1 = sync read
)(
  input  logic                    clk,        // only used if SYNC_READ=1
  input  logic [ADDR_WIDTH+1:0]  addr,       // full byte address: PC[ADDR_WIDTH+1:0]
  output logic [DATA_WIDTH-1:0]  instruction // instruction at addr
);

  // Number of entries: 2^ADDR_WIDTH
  localparam DEPTH = 1 << ADDR_WIDTH;

  // Memory array: word‑addressed
  logic [DATA_WIDTH-1:0] mem [0:DEPTH-1];

  // Load instructions at time 0
  initial begin
    $display("Loading program from %s ...", MEM_FILE);
    $readmemh(MEM_FILE, mem);
  end

  // Compute word index by dropping the two LSBs of byte address
  wire [ADDR_WIDTH-1:0] waddr = addr[ADDR_WIDTH+1:2];

  generate
    if (SYNC_READ) begin : SYNC
      // synchronous read: register the output
      always_ff @(posedge clk) begin
        instruction <= mem[waddr];
      end
    end else begin : ASYNC
      // asynchronous read: combinational
      assign instruction = mem[waddr];
    end
  endgenerate

endmodule

waveInsMem.vcd
$version Generated by VerilatedVcd $end
$timescale 1ps $end
 $scope module TOP $end
  $var wire 1 # clk $end
  $var wire 12 $ addr [11:0] $end
  $var wire 32 % instruction [31:0] $end
  $scope module InstructionMemory $end
   $var wire 32 ' ADDR_WIDTH [31:0] $end
   $var wire 32 ( DATA_WIDTH [31:0] $end
   $var wire 88 ) MEM_FILE [87:0] $end
   $var wire 32 , SYNC_READ [31:0] $end
   $var wire 1 # clk $end
   $var wire 12 $ addr [11:0] $end
   $var wire 32 % instruction [31:0] $end
   $var wire 32 - DEPTH [31:0] $end
   $var wire 10 & waddr [9:0] $end
  $upscope $end
 $upscope $end
$enddefinitions $end


#0
1#
b000000000001 $
b00000000000000000000000000000000 %
b0000000000 &
b00000000000000000000000000001010 '
b00000000000000000000000000100000 (
b0111000001110010011011110110011101110010011000010110110100101110011010000110010101111000 )
b00000000000000000000000000000001 ,
b00000000000000000000010000000000 -
#1
0#
b000000000010 $
#2
1#
b000000000011 $
b00000000101001011000010100110011 %
#3
0#
b000000000100 $
b0000000001 &
#4
1#
b000000000101 $
b01000000101101010000010100110011 %
#5
0#
b000000000110 $
#6
1#
b000000000111 $
#7
0#
b000000001000 $
b0000000010 &
#8
1#
b000000001001 $
b00000000000100000000010100010011 %
#9
0#
b000000001010 $
#10
1#
b000000001011 $
#11
0#
b000000001100 $
b0000000011 &
#12
1#
b000000001101 $
b11111111111101010000010100010011 %
#13
0#
b000000001110 $
#14
1#
b000000001111 $
#15
0#
b000000010000 $
b0000000100 &
#16
1#
b000000010001 $
b00000000000000000010011110000011 %
#17
0#
b000000010010 $
#18
1#
b000000010011 $
#19
0#
b000000010100 $
b0000000101 &
#20
1#
b000000010101 $
b00000000101001010010000000100011 %
#21
0#
b000000010110 $
#22
1#
b000000010111 $
#23
0#
b000000011000 $
b0000000110 &
#24
1#
b000000011001 $
b00000000101101010000010001100011 %
#25
0#
b000000011010 $
#26
1#
b000000011011 $
#27
0#
b000000011100 $
b0000000111 &
#28
1#
b000000011101 $
b00000000010000000000000011101111 %
#29
0#
b000000011110 $
