smolInsDec.sv
/*

Author: Ricardo Vergel

Description: SmolCore Instruction decoder and immediate generator

Date: April 18-2025

*****INSERT HERE YOUR CHANGES COMMENTS + DATE *****
Date: May 21-2025
Description: Fixed case logic after TB
*/

/* verilator lint_off WIDTHTRUNC */
/* verilator lint_off WIDTHEXPAND */
/* verilator lint_off CASEOVERLAP */

module smolInsDec(
    input logic [31:0] instr,

    // decoded fields

    output logic [6:0] opcode,
    output logic [4:0] rd,
    output logic [2:0] funct3,
    output logic [4:0] rs1,
    output logic [4:0] rs2,
    output logic [6:0] funct7,

    //inmediates

    output logic [31:0] imm


);

//1) Field extraction
assign opcode = instr[6:0];
assign rd     = instr[11:7];
assign funct3 = instr[14:12];
assign rs1    = instr[19:15];
assign rs2    = instr[24:20];
assign funct7 = instr[31:25];        // bit 30 differentiates e.g. add vs sub

// 2) Ins Type selection
logic [2:0] optype;
logic [4:0] internal;
assign internal = instr[6:2];
always_comb begin
casez (internal)

    5'b00101, 5'b01101: begin
                            optype = 3'b001; //U TYPE
                            end

    5'b00000,5'b00001,5'b00100,5'b00110,5'b11001: begin
                                                                optype = 3'b010; //I TYPE
                                                                end

    5'b01000,5'b01001: begin
                            optype = 3'b011; //S TYPE
                            end

    5'b01100,5'b01110,5'b01011,5'b10100: begin                                                                                                                      optype = 3'b100; //R TYPE
                                                    end

                                                                                                                              5'b11011: begin
               optype = 3'b101; //J TYPE
               end
                                                                                                                              5'b11000: begin
               optype = 3'b110; //B TYPE
               end
                                                                                                                               default: begin
             optype = 3'b111;
             end  
endcase  
                                                                                                                          
end

// IMMEDIATE GENERATOR + SHAMT GENERATOR IF I INSTRCTION                                                                                                                          
always_comb begin 

case (optype)
    3'b001: begin
    imm = {instr[31:12],1'b0}; //U IMMEDIATE
end
3'b010: begin
imm = {{20{instr[31]}}, instr[31:20]}; // I INMEDIATE
end
3'b011: begin
imm = {{20{instr[31]}},instr[31:25],instr[11:7]}; // S IMMEDIATE
end
3'b101: begin
imm = {{11{instr[31]}},instr[19:12],instr[20],instr[30:21],1'b0}; //J IMMEDIATE
end

3'b110: begin
imm = {{20{instr[31]}},instr[7],instr[30:25],instr[11:8],1'b0};
end
default: begin
imm = 32'h0000_0000;
end
endcase
end
endmodule

waveDecoder.vcd
$version Generated by VerilatedVcd $end
$timescale 1ps $end
 $scope module TOP $end
  $var wire 32 # instr [31:0] $end
  $var wire 7 $ opcode [6:0] $end
  $var wire 5 % rd [4:0] $end
  $var wire 3 & funct3 [2:0] $end
  $var wire 5 ' rs1 [4:0] $end
  $var wire 5 ( rs2 [4:0] $end
  $var wire 7 ) funct7 [6:0] $end
  $var wire 32 * imm [31:0] $end
  $scope module smolInsDec $end
   $var wire 32 # instr [31:0] $end
   $var wire 7 $ opcode [6:0] $end
   $var wire 5 % rd [4:0] $end
   $var wire 3 & funct3 [2:0] $end
   $var wire 5 ' rs1 [4:0] $end
   $var wire 5 ( rs2 [4:0] $end
   $var wire 7 ) funct7 [6:0] $end
   $var wire 32 * imm [31:0] $end
   $var wire 3 + optype [2:0] $end
   $var wire 5 , internal [4:0] $end
  $upscope $end
 $upscope $end
$enddefinitions $end


#0
b00000000000000000000000000000000 #
b0000000 $
b00000 %
b000 &
b00000 '
b00000 (
b0000000 )
b00000000000000000000000000000000 *
b010 +
b00000 ,
#1
#2
b00000000101001011000010100110011 #
b0110011 $
b01010 %
b01011 '
b01010 (
b100 +
b01100 ,
#3
#4
b00000000110001101000011010110011 #
b01101 %
b01101 '
b01100 (
#5
#6
b00000000000100000000010100010011 #
b0010011 $
b01010 %
b00000 '
b00001 (
b00000000000000000000000000000001 *
b010 +
b00100 ,
#7
#8
b00000000000001011000010110010011 #
b01011 %
b01011 '
b00000 (
b00000000000000000000000000000000 *
#9
#10
b00000000000000000010011110000011 #
b0000011 $
b01111 %
b010 &
b00000 '
b00000 ,
#11
#12
b00000000101101010010001000100011 #
b0100011 $
b00100 %
b01010 '
b01011 (
b00000000000000000000000000000100 *
b011 +
b01000 ,
#13
#14
b11111110010100011001101011100011 #
b1100011 $
b10101 %
b001 &
b00011 '
b00101 (
b1111111 )
b11111111111111111111111111110100 *
b110 +
b11000 ,
#15
#16
b00000000101101010000010001100011 #
b01000 %
b000 &
b01010 '
b01011 (
b0000000 )
b00000000000000000000000000001000 *
#17
#18
b00000000000000000000001010110111 #
b0110111 $
b00101 %
b00000 '
b00000 (
b00000000000000000000000000000000 *
b001 +
b01101 ,
#19
#20
b00000000010000000000000011101111 #
b1101111 $
b00001 %
b00100 (
b00000000000000000000000000000100 *
b101 +
b11011 ,
