smolPC.sv
module smolPC (
  input logic clk,
  input logic rst,
  input logic [31:0] next_pc,	// pc+4 or branch tgt
  output logic [31:0] pc	
);

  always_ff @(posedge clk) begin
   if (rst)
    pc <= 32'h0000_0000;
   else
    pc <= next_pc;
  end
endmodule

testBench/PC_tb.sv
`timescale 1ns/1ps

module PC_tb();

logic clk;
logic rst;
logic [31:0] next_pc;

logic [31:0] pc;

smolPC dut(
    .clk(clk),
    .rst(rst),
    .next_pc(next_pc),
    .pc(pc)
);


initial begin
    rst = 1'b1; #10;
    rst = 1'b0; #5;

    next_pc = 32'h0000_000A; #10;
    next_pc = 32'h0000_000E; #10;
    next_pc = 32'h1234_5678; #10;
    next_pc = 32'h0000_0000; 


end


always begin
    clk = 1'b1; #5;
    clk = 1'b0; #5;
end

initial begin
    $display("Starting PC testbench");
    $dumpfile("PC.vcd");
    $dumpvars;
    #500;
    $display("End of simulation");
    $finish;
end

endmodule

testBench/PC.vcd
$date
	Fri May 16 18:08:19 2025
$end
$version
	Icarus Verilog
$end
$timescale
	1ps
$end
$scope module PC_tb $end
$var wire 32 ! pc [31:0] $end
$var reg 1 " clk $end
$var reg 32 # next_pc [31:0] $end
$var reg 1 $ rst $end
$scope module dut $end
$var wire 1 " clk $end
$var wire 32 % next_pc [31:0] $end
$var wire 1 $ rst $end
$var reg 32 & pc [31:0] $end
$upscope $end
$upscope $end
$enddefinitions $end
$comment Show the parameter values. $end
$dumpall
$end
#0
$dumpvars
b0 &
bx %
1$
bx #
1"
b0 !
$end
#5000
0"
#10000
bx !
bx &
1"
0$
#15000
0"
b1010 #
b1010 %
#20000
b1010 !
b1010 &
1"
#25000
0"
b1110 #
b1110 %
#30000
b1110 !
b1110 &
1"
#35000
0"
b10010001101000101011001111000 #
b10010001101000101011001111000 %
#40000
b0 !
b0 &
1"
b0 #
b0 %
