smolRF.sv
/*
    Author: Ricardo Vergel
    Description: 32x32 register file for SmolCore
    Date: April 19-2025

    ****COMMENT YOUR CHANGES BELOW****
    Date: May 16-2025
    Description: MOdified X0 assignment
*/
module smolRF (
    input logic clk,
    input logic rst,
    input logic wEnable,
    input logic rEnable1,
    input logic rEnable2,
    input logic [4:0] wAddr,
    input logic [31:0] wData,
    input logic [4:0] rAddr1,
    input logic [4:0] rAddr2,
    output logic [31:0] rData1,
    output logic [31:0] rData2
);

//REGISTER FILE DECLARATION

logic [31:0] registerFile [0:31];


//ASYNCRONOUS READ PROT

assign rData1 = rEnable1 ? registerFile[rAddr1] : 32'd0;
assign rData2 = rEnable2 ? registerFile[rAddr2] : 32'd0;

//SYNCRONOUS WRITE PORT

always_ff @(posedge clk) begin
    if (rst) begin
        for (int i = 0; i < 32; i++)
            registerFile[i] <= 32'h0000_0000;
    end else if (wEnable && wAddr != 5'd0) begin
        registerFile[wAddr] <= wData;
    end
end

endmodule

testBench/RF_tb.sv
`timescale 1ns/1ps

module RF_tb;

logic clk;
logic rst;
logic wEnable;
logic rEnable1;
logic rEnable2;
logic [4:0] wAddr;
logic [31:0] wData;
logic [4:0] rAddr1;
logic [4:0] rAddr2;

logic [31:0] rData1;
logic[31:0] rData2;

smolRF dut(
    .clk(clk),
    .rst(rst),
    .wEnable(wEnable),
    .rEnable1(rEnable1),
    .rEnable2(rEnable2),
    .wAddr(wAddr),
    .wData(wData),
    .rAddr1(rAddr1),
    .rAddr2(rAddr2),
    .rData1(rData1),
    .rData2(rData2)
);

initial begin
    rst = 1'b1;		
    wEnable = 1'b0; rEnable1 = 1'b0; rEnable2= 1'b0;
    #20;

    rst = 1'b0;

    wEnable = 1'b1; #10;
    wData = 32'h0000_0010; wAddr = 5'b000_01; #20;
    wEnable = 1'b0;

    rEnable1 = 1'b1; #10;
    rAddr1 = 5'b000_01; #20;
    
    wEnable = 1'b1; #50;
    wData = 32'h0000_0001; wAddr = 5'b000_10; #10;
    wData = 32'h0000_0002; wAddr = 5'b000_11;
    #10;

    rEnable2 = 1'b1; #10;
    rAddr2 = 5'b000_10; #5;

    rEnable1 = 1'b0;
    rAddr2 = 5'b000_11; #10;
    
end


always begin
    clk <= 1'b1;	#5;
    clk <= 1'b0;	#5;
end

initial begin
    $display("Starting Register File Testbench...");
    $dumpfile("RF.vcd");
    $dumpvars;
    #1000;
    $finish;
end

endmodule

testBench/RF.vcd
$date
	Fri May 16 17:52:20 2025
$end
$version
	Icarus Verilog
$end
$timescale
	1ps
$end
$scope module RF_tb $end
$var wire 32 ! rData2 [31:0] $end
$var wire 32 " rData1 [31:0] $end
$var reg 1 # clk $end
$var reg 5 $ rAddr1 [4:0] $end
$var reg 5 % rAddr2 [4:0] $end
$var reg 1 & rEnable1 $end
$var reg 1 ' rEnable2 $end
$var reg 1 ( rst $end
$var reg 5 ) wAddr [4:0] $end
$var reg 32 * wData [31:0] $end
$var reg 1 + wEnable $end
$scope module dut $end
$var wire 1 # clk $end
$var wire 5 , rAddr1 [4:0] $end
$var wire 5 - rAddr2 [4:0] $end
$var wire 1 & rEnable1 $end
$var wire 1 ' rEnable2 $end
$var wire 1 ( rst $end
$var wire 5 . wAddr [4:0] $end
$var wire 32 / wData [31:0] $end
$var wire 1 + wEnable $end
$var wire 32 0 rData2 [31:0] $end
$var wire 32 1 rData1 [31:0] $end
$scope begin $ivl_for_loop0 $end
$var integer 32 2 i [31:0] $end
$upscope $end
$upscope $end
$upscope $end
$enddefinitions $end
$comment Show the parameter values. $end
$dumpall
$end
#0
$dumpvars
b100000 2
b0 1
b0 0
bx /
bx .
bx -
bx ,
0+
bx *
bx )
1(
0'
0&
bx %
bx $
1#
b0 "
b0 !
$end
#5000
0#
#10000
b100000 2
1#
#15000
0#
#20000
1#
1+
0(
#25000
0#
#30000
1#
b1 )
b1 .
b10000 *
b10000 /
#35000
0#
#40000
1#
#45000
0#
#50000
1#
bx "
bx 1
1&
0+
#55000
0#
#60000
1#
b10000 "
b10000 1
b1 $
b1 ,
#65000
0#
#70000
1#
#75000
0#
#80000
1#
1+
#85000
0#
#90000
1#
#95000
0#
#100000
1#
#105000
0#
#110000
1#
#115000
0#
#120000
1#
#125000
0#
#130000
1#
b10 )
b10 .
b1 *
b1 /
#135000
0#
#140000
1#
b11 )
b11 .
b10 *
b10 /
#145000
0#
#150000
1#
bx !
bx 0
1'
#155000
0#
#160000
1#
b1 !
b1 0
b10 %
b10 -
#165000
0#
b10 !
b10 0
b0 "
b0 1
b11 %
b11 -
0&
